README.rst
setup.cfg
setup.py
gutter/__init__.py
gutter/client/__init__.py
gutter/client/compat.py
gutter/client/encoding.py
gutter/client/models.py
gutter/client/registry.py
gutter/client/signals.py
gutter/client/testutils.py
gutter/client/arguments/__init__.py
gutter/client/arguments/base.py
gutter/client/arguments/variables.py
gutter/client/operators/__init__.py
gutter/client/operators/comparable.py
gutter/client/operators/identity.py
gutter/client/operators/misc.py
gutter/client/operators/string.py
gutter_python3.egg-info/PKG-INFO
gutter_python3.egg-info/SOURCES.txt
gutter_python3.egg-info/dependency_links.txt
gutter_python3.egg-info/namespace_packages.txt
gutter_python3.egg-info/not-zip-safe
gutter_python3.egg-info/requires.txt
gutter_python3.egg-info/top_level.txt